Metadata-Version: 1.0
Name: axl
Version: 0.5.1
Summary: Python package that generates web extensions for Firefox
Home-page: http://github.com/justinpotts/axl
Author: Justin Potts
Author-email: jpotts@mozilla.com
License: MPL
Platform: UNKNOWN
